lineopt.py
lineopt-0.0.4.dist-info/LICENCE
lineopt-0.0.4.dist-info/METADATA
lineopt-0.0.4.dist-info/WHEEL
lineopt-0.0.4.dist-info/top_level.txt
lineopt-0.0.4.dist-info/RECORD
