Metadata-Version: 2.1
Name: lineopt
Version: 0.0.4
Summary: Command line based invoke framework.
Home-page: https://github.com/Exahilosys/lineopt
License: MIT
Platform: UNKNOWN
Requires-Dist: flagopt
Provides-Extra: docs
Requires-Dist: sphinx ; extra == 'docs'
